wpylib/__init__.py
wpylib/middleware/__init__.py
wpylib/middleware/validate_get_params.py
wpylib/middleware/validate_post_params.py
wpylib/pkg/__init__.py
wpylib/pkg/langchain/__init__.py
wpylib/pkg/langchain/chain.py
wpylib/pkg/langchain/history.py
wpylib/pkg/langchain/log_callback.py
wpylib/pkg/langchain/model.py
wpylib/pkg/langchain/prompt.py
wpylib/pkg/singleton/__init__.py
wpylib/pkg/singleton/flask/__init__.py
wpylib/pkg/singleton/flask/flask.py
wpylib/pkg/singleton/loader/__init__.py
wpylib/pkg/singleton/loader/simple_web_document.py
wpylib/pkg/singleton/loader/web_loader.py
wpylib/pkg/singleton/localcache/__init__.py
wpylib/pkg/singleton/localcache/localcache.py
wpylib/pkg/singleton/logger/__init__.py
wpylib/pkg/singleton/logger/logger.py
wpylib/pkg/singleton/milvus/__init__.py
wpylib/pkg/singleton/milvus/milvus.py
wpylib/pkg/singleton/mysql/__init__.py
wpylib/pkg/singleton/mysql/mysql.py
wpylib/pkg/sse/__init__.py
wpylib/pkg/sse/stream_queue.py
wpylib/pkg/sse/stream_response.py
wpylib/util/__init__.py
wpylib/util/cmd.py
wpylib/util/encry.py
wpylib/util/http.py
wpylib/util/sql/__init__.py
wpylib/util/sql/binding.py
wpylib/util/storage.py
wpylib/util/x/__init__.py
wpylib/util/x/xjson.py
wpylib/util/x/xtime.py
wpylib/util/x/xtyping.py
wpylib-0.0.12.dist-info/LICENSE
wpylib-0.0.12.dist-info/METADATA
wpylib-0.0.12.dist-info/WHEEL
wpylib-0.0.12.dist-info/RECORD
