Metadata-Version: 2.1
Name: wpylib
Version: 0.0.12
Summary: A simple and easy-to-use library in python
License: MIT
Author: Wgrape
Requires-Python: >=3.10,<4.0
Classifier: License :: OSI Approved :: MIT License
Classifier: Programming Language :: Python :: 3
Classifier: Programming Language :: Python :: 3.10
Classifier: Programming Language :: Python :: 3.11
Classifier: Programming Language :: Python :: 3.12
